<?xml version="1.0" encoding="UTF-8"?>
<suite name="8PMproject" verbose="1">
<test name="sanity testing">
 <parameter name="Uname" value= "admin1"/>
 <parameter name="Pword" value= "admin@123"/>
 <parameter name="CPword" value= "admin@123"/>
 <parameter name="Email" value= "admin123@gmail.com"/>
<classes>
 <class name ="testNGScripts.ParameterizationwithXML"/>
 </classes>
</test>

<test name="Regression testing">
 <parameter name="Uname" value= "Emp1"/>
 <parameter name="Pword" value= "emp@123"/>
  <parameter name="CPword" value= "emp@123"/>
 <parameter name="Email" value= "emp123@gmail.com"/>
<classes>
 <class name ="testNGScripts.ParameterizationwithXML"/>
 </classes>
</test>





</suite>
